jasmin_mongo_logger/__init__.py
jasmin_mongo_logger/__main__.py
jasmin_mongo_logger/logreactor.py
jasmin_mongo_logger/mongodb.py
jasmin_mongo_logger/specs/amqp0-9-1.xml
jasmin_mongo_logger-0.2.0.dist-info/METADATA
jasmin_mongo_logger-0.2.0.dist-info/WHEEL
jasmin_mongo_logger-0.2.0.dist-info/entry_points.txt
jasmin_mongo_logger-0.2.0.dist-info/licenses/LICENSE
jasmin_mongo_logger-0.2.0.dist-info/RECORD
