Metadata-Version: 2.1
Name: jasmin_mongo_logger
Version: 0.2.0
Summary: Log Jasmin SMS Gateway MT/MO to MongoDB Cluster.
Project-URL: Homepage, https://github.com/BlackOrder/jasmin_mongo_logger
Project-URL: Bug Tracker, https://github.com/BlackOrder/jasmin_mongo_logger/issues
Project-URL: Source Code, https://github.com/BlackOrder/jasmin_mongo_logger
Author-email: BlackOrder <4302157+BlackOrder@users.noreply.github.com>
License-File: LICENSE
Classifier: License :: OSI Approved :: GNU General Public License v3 (GPLv3)
Classifier: Operating System :: OS Independent
Classifier: Programming Language :: Python :: 3
Requires-Python: >=3.11
Requires-Dist: dnspython
Requires-Dist: pymongo
Requires-Dist: smpp-pdu3
Requires-Dist: twisted
Requires-Dist: txamqp
